yojenkins/__init__.py
yojenkins/__main__.py
yojenkins/cli/__init__.py
yojenkins/cli/cli_account.py
yojenkins/cli/cli_auth.py
yojenkins/cli/cli_build.py
yojenkins/cli/cli_credential.py
yojenkins/cli/cli_decorators.py
yojenkins/cli/cli_folder.py
yojenkins/cli/cli_job.py
yojenkins/cli/cli_node.py
yojenkins/cli/cli_server.py
yojenkins/cli/cli_stage.py
yojenkins/cli/cli_step.py
yojenkins/cli/cli_tools.py
yojenkins/cli/cli_utility.py
yojenkins/cli/logger_setup.py
yojenkins/cli_sub_commands/__init__.py
yojenkins/cli_sub_commands/account.py
yojenkins/cli_sub_commands/auth.py
yojenkins/cli_sub_commands/build.py
yojenkins/cli_sub_commands/credential.py
yojenkins/cli_sub_commands/folder.py
yojenkins/cli_sub_commands/job.py
yojenkins/cli_sub_commands/node.py
yojenkins/cli_sub_commands/server.py
yojenkins/cli_sub_commands/stage.py
yojenkins/cli_sub_commands/step.py
yojenkins/cli_sub_commands/tools.py
yojenkins/docker_container/__init__.py
yojenkins/docker_container/docker_jenkins_server.py
yojenkins/monitor/__init__.py
yojenkins/monitor/build_monitor.py
yojenkins/monitor/folder_monitor.py
yojenkins/monitor/job_monitor.py
yojenkins/monitor/monitor.py
yojenkins/monitor/monitor_utility.py
yojenkins/resources/scripts/node_prepare_amazonlinux2.sh
yojenkins/resources/server_docker_settings/Dockerfile
yojenkins/resources/server_docker_settings/config_as_code.yaml
yojenkins/resources/server_docker_settings/dummy.sh
yojenkins/resources/server_docker_settings/plugins.txt
yojenkins/resources/sound/negative_alert_wooden_mallet_fast_negative_error_two_tone.wav
yojenkins/resources/sound/negative_notification_mallet_wooden_short_alert.wav
yojenkins/resources/sound/negative_ui_ping_chime_mallet_like.wav
yojenkins/resources/sound/negative_ui_ping_chime_mallet_like_error.wav
yojenkins/resources/sound/positive_alert_mallet_wood_simple_musical_003.wav
yojenkins/resources/sound/positive_alert_notification_musical_short_marimba_process_finished.wav
yojenkins/tools/__init__.py
yojenkins-0.1.2.dist-info/licenses/LICENSE
yojenkins-0.1.2.dist-info/METADATA
yojenkins-0.1.2.dist-info/WHEEL
yojenkins-0.1.2.dist-info/entry_points.txt
yojenkins-0.1.2.dist-info/top_level.txt
yojenkins-0.1.2.dist-info/RECORD
