Metadata-Version: 2.4
Name: yojenkins
Version: 0.1.2
Summary: A CLI tool to manage and have fun with Jenkins server
Home-page: https://github.com/ismet55555/yojenkins
Author: Ismet Handzic
Author-email: ismet.handzic@gmail.com
Maintainer: Ismet Handzic
Keywords: jenkins monitor manage job build fun
Classifier: Development Status :: 4 - Beta
Classifier: License :: OSI Approved :: Apache Software License
Classifier: Natural Language :: English
Classifier: Intended Audience :: System Administrators
Classifier: Intended Audience :: Developers
Classifier: Topic :: Utilities
Classifier: Topic :: Software Development :: Testing
Classifier: Topic :: System :: Monitoring
Classifier: Topic :: Software Development :: Libraries :: Python Modules
Classifier: Environment :: Console
Classifier: Environment :: Console :: Curses
Classifier: Operating System :: OS Independent
Classifier: Programming Language :: Python :: 3 :: Only
Requires-Python: >=3.7
License-File: LICENSE
Requires-Dist: PyYAML==6.0
Requires-Dist: click-help-colors==0.9.4
Requires-Dist: click==8.2.1
Requires-Dist: coloredlogs==15.0.1
Requires-Dist: docker==7.1.0
Requires-Dist: json2xml
Requires-Dist: pypiwin32; platform_system == "Windows"
Requires-Dist: python-jenkins==1.8.2
Requires-Dist: pywin32; platform_system == "Windows"
Requires-Dist: requests-futures==1.0.2
Requires-Dist: toml==0.10.2
Requires-Dist: windows-curses; sys_platform == "win32"
Requires-Dist: xmltodict
Requires-Dist: yaspin==3.1.0
Provides-Extra: sound
Requires-Dist: simpleaudio; sys_platform != "win32" and extra == "sound"
Dynamic: author
Dynamic: author-email
Dynamic: classifier
Dynamic: description
Dynamic: description-content-type
Dynamic: home-page
Dynamic: keywords
Dynamic: license-file
Dynamic: maintainer
Dynamic: provides-extra
Dynamic: requires-dist
Dynamic: requires-python
Dynamic: summary
